bm_fastapi_tracer/__init__.py
bm_flask_tracer/__init__.py
bm_opentracing_tracer/__init__.py
bm_opentracing_tracer/bm_jaeger_tracer.py
bm_opentracing_tracer-0.0.5.dist-info/LICENSE
bm_opentracing_tracer-0.0.5.dist-info/METADATA
bm_opentracing_tracer-0.0.5.dist-info/WHEEL
bm_opentracing_tracer-0.0.5.dist-info/top_level.txt
bm_opentracing_tracer-0.0.5.dist-info/RECORD
