Metadata-Version: 2.1
Name: bm-opentracing-tracer
Version: 0.0.5
Summary: UNKNOWN
Home-page: https://github.com/beyondminds/bm-opentracing
Author: Vadim Geshiktor
Author-email: vadim.geshiktor@beyoundminds.ai
License: UNKNOWN
Platform: UNKNOWN
Classifier: Programming Language :: Python :: 3
Classifier: Operating System :: OS Independent
Requires-Python: >=3.6
